{
    "topology": "topologies/zoo_Quest.json",
    "method": {
        "name": "inout-disjoint",
        "path_heuristic": "greedy_min_congestion",
        "mem_per_router_per_flow": 3
    },
    "flows": "flows.yml",
    "failure_scenarios": "failure_scenarios.yml",
    "flows#": 76,
    "failure_scenarios#": 332,
    "ft_gen_time": 3043336684,
    "simulation_time": 6765638803,
    "runs": [
        {
            "failed_links#": 0,
            "delivered_packet_rate": 1.0,
            "median_congestion": 0.413389,
            "max_congestion": 0.635206,
            "path_stretch": 1.8186008332440284,
            "fortz_thorup_sum": 136
        },
        {
            "failed_links#": 1,
            "delivered_packet_rate": 1.0,
            "median_congestion": 0.465354,
            "max_congestion": 0.930298,
            "path_stretch": 2.069124726729282,
            "fortz_thorup_sum": 694
        },
        {
            "failed_links#": 1,
            "delivered_packet_rate": 0.9834972893023247,
            "median_congestion": 0.371492,
            "max_congestion": 0.87924,
            "path_stretch": 1.827165368195827,
            "fortz_thorup_sum": 170
        },
        {
            "failed_links#": 1,
            "delivered_packet_rate": 0.9841190352748175,
            "median_congestion": 0.358844,
            "max_congestion": 0.961529,
            "path_stretch": 1.837023744592882,
            "fortz_thorup_sum": 656
        },
        {
            "failed_links#": 1,
            "delivered_packet_rate": 0.992437931250001,
            "median_congestion": 0.367162,
            "max_congestion": 0.951687,
            "path_stretch": 1.8855231684031046,
            "fortz_thorup_sum": 663
        },
        {
            "failed_links#": 1,
            "delivered_packet_rate": 0.9899017846079022,
            "median_congestion": 0.390559,
            "max_congestion": 0.918695,
            "path_stretch": 1.832939444994703,
            "fortz_thorup_sum": 675
        },
        {
            "failed_links#": 1,
            "delivered_packet_rate": 0.9830813445035655,
            "median_congestion": 0.390559,
            "max_congestion": 1.053186,
            "path_stretch": 1.8423935090531238,
            "fortz_thorup_sum": 1652
        },
        {
            "failed_links#": 1,
            "delivered_packet_rate": 1.0,
            "median_congestion": 0.3736,
            "max_congestion": 0.769155,
            "path_stretch": 1.8197221136178603,
            "fortz_thorup_sum": 158
        },
        {
            "failed_links#": 1,
            "delivered_packet_rate": 0.9386748172409585,
            "median_congestion": 0.405807,
            "max_congestion": 0.869466,
            "path_stretch": 1.8244841546780914,
            "fortz_thorup_sum": 150
        },
        {
            "failed_links#": 1,
            "delivered_packet_rate": 0.9484703017429824,
            "median_congestion": 0.390559,
            "max_congestion": 0.776394,
            "path_stretch": 1.8504694195445428,
            "fortz_thorup_sum": 176
        },
        {
            "failed_links#": 1,
            "delivered_packet_rate": 0.9899017846079022,
            "median_congestion": 0.390559,
            "max_congestion": 0.918695,
            "path_stretch": 1.832939444994703,
            "fortz_thorup_sum": 675
        },
        {
            "failed_links#": 1,
            "delivered_packet_rate": 0.9834972893023247,
            "median_congestion": 0.373702,
            "max_congestion": 0.87603,
            "path_stretch": 1.815554059604453,
            "fortz_thorup_sum": 165
        },
        {
            "failed_links#": 1,
            "delivered_packet_rate": 0.9484703017429824,
            "median_congestion": 0.390559,
            "max_congestion": 0.776394,
            "path_stretch": 1.8504694195445428,
            "fortz_thorup_sum": 176
        },
        {
            "failed_links#": 1,
            "delivered_packet_rate": 0.9897558472269804,
            "median_congestion": 0.374957,
            "max_congestion": 0.832327,
            "path_stretch": 1.8699627818203632,
            "fortz_thorup_sum": 193
        },
        {
            "failed_links#": 1,
            "delivered_packet_rate": 0.9462855834804468,
            "median_congestion": 0.438265,
            "max_congestion": 0.7315,
            "path_stretch": 1.9177445931589994,
            "fortz_thorup_sum": 167
        },
        {
            "failed_links#": 1,
            "delivered_packet_rate": 0.992437931250001,
            "median_congestion": 0.367162,
            "max_congestion": 0.951687,
            "path_stretch": 1.8855231684031046,
            "fortz_thorup_sum": 663
        },
        {
            "failed_links#": 1,
            "delivered_packet_rate": 0.946167716945377,
            "median_congestion": 0.44554,
            "max_congestion": 0.849467,
            "path_stretch": 1.9796757846131687,
            "fortz_thorup_sum": 178
        },
        {
            "failed_links#": 1,
            "delivered_packet_rate": 0.9386748172409585,
            "median_congestion": 0.405807,
            "max_congestion": 0.869466,
            "path_stretch": 1.8244841546780914,
            "fortz_thorup_sum": 150
        },
        {
            "failed_links#": 1,
            "delivered_packet_rate": 0.9484703017429824,
            "median_congestion": 0.390559,
            "max_congestion": 0.776394,
            "path_stretch": 1.8504694195445428,
            "fortz_thorup_sum": 176
        },
        {
            "failed_links#": 1,
            "delivered_packet_rate": 0.9631150636378483,
            "median_congestion": 0.427468,
            "max_congestion": 0.78819,
            "path_stretch": 1.9072093513327184,
            "fortz_thorup_sum": 173
        },
        {
            "failed_links#": 1,
            "delivered_packet_rate": 0.9549236496255954,
            "median_congestion": 0.390559,
            "max_congestion": 0.76642,
            "path_stretch": 1.8709950378844478,
            "fortz_thorup_sum": 157
        },
        {
            "failed_links#": 1,
            "delivered_packet_rate": 0.989303146679785,
            "median_congestion": 0.433885,
            "max_congestion": 0.806516,
            "path_stretch": 1.888821661333018,
            "fortz_thorup_sum": 187
        },
        {
            "failed_links#": 1,
            "delivered_packet_rate": 0.9462855834804468,
            "median_congestion": 0.438265,
            "max_congestion": 0.7315,
            "path_stretch": 1.9177445931589994,
            "fortz_thorup_sum": 167
        },
        {
            "failed_links#": 1,
            "delivered_packet_rate": 0.9537826705486113,
            "median_congestion": 0.374957,
            "max_congestion": 0.85839,
            "path_stretch": 1.8751186578954484,
            "fortz_thorup_sum": 166
        },
        {
            "failed_links#": 1,
            "delivered_packet_rate": 1.0,
            "median_congestion": 0.374957,
            "max_congestion": 0.760011,
            "path_stretch": 1.8077223077874676,
            "fortz_thorup_sum": 165
        },
        {
            "failed_links#": 1,
            "delivered_packet_rate": 0.9899017846079022,
            "median_congestion": 0.390559,
            "max_congestion": 0.918695,
            "path_stretch": 1.832939444994703,
            "fortz_thorup_sum": 675
        },
        {
            "failed_links#": 1,
            "delivered_packet_rate": 0.9899017846079022,
            "median_congestion": 0.390559,
            "max_congestion": 0.918695,
            "path_stretch": 1.832939444994703,
            "fortz_thorup_sum": 675
        },
        {
            "failed_links#": 1,
            "delivered_packet_rate": 0.9631150636378483,
            "median_congestion": 0.427468,
            "max_congestion": 0.78819,
            "path_stretch": 1.9072093513327184,
            "fortz_thorup_sum": 173
        },
        {
            "failed_links#": 1,
            "delivered_packet_rate": 0.9921792452230321,
            "median_congestion": 0.383291,
            "max_congestion": 0.773204,
            "path_stretch": 1.7945700534304079,
            "fortz_thorup_sum": 178
        },
        {
            "failed_links#": 1,
            "delivered_packet_rate": 0.9834972893023247,
            "median_congestion": 0.373702,
            "max_congestion": 0.87603,
            "path_stretch": 1.815554059604453,
            "fortz_thorup_sum": 165
        },
        {
            "failed_links#": 1,
            "delivered_packet_rate": 1.0,
            "median_congestion": 0.3736,
            "max_congestion": 0.769155,
            "path_stretch": 1.8197221136178603,
            "fortz_thorup_sum": 158
        },
        {
            "failed_links#": 1,
            "delivered_packet_rate": 0.9897558472269804,
            "median_congestion": 0.360665,
            "max_congestion": 0.832327,
            "path_stretch": 1.839986966298684,
            "fortz_thorup_sum": 189
        },
        {
            "failed_links#": 2,
            "delivered_packet_rate": 0.9630558201952211,
            "median_congestion": 0.410798,
            "max_congestion": 1.005173,
            "path_stretch": 1.9189690115575124,
            "fortz_thorup_sum": 1694
        },
        {
            "failed_links#": 2,
            "delivered_packet_rate": 0.9834972893023247,
            "median_congestion": 0.371492,
            "max_congestion": 0.87924,
            "path_stretch": 1.827165368195827,
            "fortz_thorup_sum": 170
        },
        {
            "failed_links#": 2,
            "delivered_packet_rate": 0.8935984668665539,
            "median_congestion": 0.356148,
            "max_congestion": 0.869466,
            "path_stretch": 1.8873466941116626,
            "fortz_thorup_sum": 156
        },
        {
            "failed_links#": 2,
            "delivered_packet_rate": 0.9523353935679921,
            "median_congestion": 0.415646,
            "max_congestion": 1.007839,
            "path_stretch": 1.875023744845332,
            "fortz_thorup_sum": 678
        },
        {
            "failed_links#": 2,
            "delivered_packet_rate": 0.9528709108648287,
            "median_congestion": 0.403581,
            "max_congestion": 0.887308,
            "path_stretch": 1.961512098467404,
            "fortz_thorup_sum": 224
        },
        {
            "failed_links#": 2,
            "delivered_packet_rate": 0.9451213412715411,
            "median_congestion": 0.374957,
            "max_congestion": 0.727148,
            "path_stretch": 1.8403884211790118,
            "fortz_thorup_sum": 158
        },
        {
            "failed_links#": 2,
            "delivered_packet_rate": 0.9549236496255954,
            "median_congestion": 0.390559,
            "max_congestion": 0.76642,
            "path_stretch": 1.8709950378844478,
            "fortz_thorup_sum": 157
        },
        {
            "failed_links#": 2,
            "delivered_packet_rate": 0.9462855834804468,
            "median_congestion": 0.393414,
            "max_congestion": 0.991059,
            "path_stretch": 1.9441239367717849,
            "fortz_thorup_sum": 719
        },
        {
            "failed_links#": 2,
            "delivered_packet_rate": 0.8879092353237941,
            "median_congestion": 0.416488,
            "max_congestion": 0.91461,
            "path_stretch": 1.9166568475268955,
            "fortz_thorup_sum": 675
        },
        {
            "failed_links#": 2,
            "delivered_packet_rate": 0.9528709108648287,
            "median_congestion": 0.361599,
            "max_congestion": 0.887308,
            "path_stretch": 1.9303759410407366,
            "fortz_thorup_sum": 220
        },
        {
            "failed_links#": 2,
            "delivered_packet_rate": 0.9401900225667889,
            "median_congestion": 0.373702,
            "max_congestion": 1.092258,
            "path_stretch": 1.723427628397807,
            "fortz_thorup_sum": 1674
        },
        {
            "failed_links#": 2,
            "delivered_packet_rate": 0.9657434873699029,
            "median_congestion": 0.399351,
            "max_congestion": 0.87603,
            "path_stretch": 1.8766056868332956,
            "fortz_thorup_sum": 204
        },
        {
            "failed_links#": 2,
            "delivered_packet_rate": 0.9484703017429824,
            "median_congestion": 0.390559,
            "max_congestion": 0.776394,
            "path_stretch": 1.8504694195445428,
            "fortz_thorup_sum": 176
        },
        {
            "failed_links#": 2,
            "delivered_packet_rate": 0.9814569575452495,
            "median_congestion": 0.42419,
            "max_congestion": 1.161376,
            "path_stretch": 1.84563020029583,
            "fortz_thorup_sum": 10209
        },
        {
            "failed_links#": 2,
            "delivered_packet_rate": 0.9731143331755059,
            "median_congestion": 0.43825,
            "max_congestion": 1.091125,
            "path_stretch": 1.8020697611151475,
            "fortz_thorup_sum": 1197
        },
        {
            "failed_links#": 2,
            "delivered_packet_rate": 0.9900329886719403,
            "median_congestion": 0.438265,
            "max_congestion": 1.074146,
            "path_stretch": 1.8873923717849908,
            "fortz_thorup_sum": 1710
        },
        {
            "failed_links#": 2,
            "delivered_packet_rate": 0.9657434873699029,
            "median_congestion": 0.399351,
            "max_congestion": 0.87603,
            "path_stretch": 1.8766056868332956,
            "fortz_thorup_sum": 204
        },
        {
            "failed_links#": 2,
            "delivered_packet_rate": 1.0,
            "median_congestion": 0.447556,
            "max_congestion": 0.955773,
            "path_stretch": 1.9701513830216255,
            "fortz_thorup_sum": 676
        },
        {
            "failed_links#": 2,
            "delivered_packet_rate": 0.9001257915086777,
            "median_congestion": 0.362929,
            "max_congestion": 0.939463,
            "path_stretch": 1.776392340779654,
            "fortz_thorup_sum": 1131
        },
        {
            "failed_links#": 2,
            "delivered_packet_rate": 0.9326640892150414,
            "median_congestion": 0.381041,
            "max_congestion": 0.973164,
            "path_stretch": 1.9586358033837004,
            "fortz_thorup_sum": 717
        },
        {
            "failed_links#": 2,
            "delivered_packet_rate": 0.9370107278708294,
            "median_congestion": 0.362929,
            "max_congestion": 0.852238,
            "path_stretch": 1.7363704793270285,
            "fortz_thorup_sum": 170
        },
        {
            "failed_links#": 2,
            "delivered_packet_rate": 0.9183073248933656,
            "median_congestion": 0.319111,
            "max_congestion": 0.887308,
            "path_stretch": 1.7496819067154923,
            "fortz_thorup_sum": 180
        },
        {
            "failed_links#": 2,
            "delivered_packet_rate": 0.8869853788114122,
            "median_congestion": 0.395294,
            "max_congestion": 0.752693,
            "path_stretch": 1.9594878570452752,
            "fortz_thorup_sum": 159
        },
        {
            "failed_links#": 2,
            "delivered_packet_rate": 0.9897558472269804,
            "median_congestion": 0.360665,
            "max_congestion": 0.832327,
            "path_stretch": 1.803300183941596,
            "fortz_thorup_sum": 189
        },
        {
            "failed_links#": 2,
            "delivered_packet_rate": 0.9747385650462758,
            "median_congestion": 0.396806,
            "max_congestion": 0.961529,
            "path_stretch": 1.8822250801341465,
            "fortz_thorup_sum": 1169
        },
        {
            "failed_links#": 2,
            "delivered_packet_rate": 0.9284306644679389,
            "median_congestion": 0.369307,
            "max_congestion": 0.869466,
            "path_stretch": 1.8516243265972658,
            "fortz_thorup_sum": 169
        },
        {
            "failed_links#": 2,
            "delivered_packet_rate": 0.9462334740649423,
            "median_congestion": 0.388768,
            "max_congestion": 0.952858,
            "path_stretch": 1.8560076515016677,
            "fortz_thorup_sum": 689
        },
        {
            "failed_links#": 2,
            "delivered_packet_rate": 0.9546263467996366,
            "median_congestion": 0.366248,
            "max_congestion": 0.831262,
            "path_stretch": 1.7835444053514176,
            "fortz_thorup_sum": 175
        },
        {
            "failed_links#": 2,
            "delivered_packet_rate": 0.9181863566073731,
            "median_congestion": 0.351523,
            "max_congestion": 1.056326,
            "path_stretch": 1.6286865044973857,
            "fortz_thorup_sum": 667
        },
        {
            "failed_links#": 2,
            "delivered_packet_rate": 0.9537826705486113,
            "median_congestion": 0.374957,
            "max_congestion": 0.85839,
            "path_stretch": 1.8751186578954484,
            "fortz_thorup_sum": 166
        },
        {
            "failed_links#": 2,
            "delivered_packet_rate": 0.9533946415081581,
            "median_congestion": 0.37354,
            "max_congestion": 0.937943,
            "path_stretch": 1.7341327040003456,
            "fortz_thorup_sum": 1658
        },
        {
            "failed_links#": 2,
            "delivered_packet_rate": 0.9370107278708294,
            "median_congestion": 0.373874,
            "max_congestion": 1.046536,
            "path_stretch": 1.753170659890781,
            "fortz_thorup_sum": 682
        },
        {
            "failed_links#": 2,
            "delivered_packet_rate": 0.946167716945377,
            "median_congestion": 0.447556,
            "max_congestion": 1.010754,
            "path_stretch": 1.9844221658076078,
            "fortz_thorup_sum": 681
        },
        {
            "failed_links#": 2,
            "delivered_packet_rate": 0.9157806385915818,
            "median_congestion": 0.407739,
            "max_congestion": 1.028723,
            "path_stretch": 2.0275343539386688,
            "fortz_thorup_sum": 1184
        },
        {
            "failed_links#": 2,
            "delivered_packet_rate": 0.844669431670831,
            "median_congestion": 0.387548,
            "max_congestion": 0.768626,
            "path_stretch": 1.9385952945588811,
            "fortz_thorup_sum": 167
        },
        {
            "failed_links#": 2,
            "delivered_packet_rate": 0.9841190352748175,
            "median_congestion": 0.358844,
            "max_congestion": 0.961529,
            "path_stretch": 1.837023744592882,
            "fortz_thorup_sum": 656
        },
        {
            "failed_links#": 2,
            "delivered_packet_rate": 0.9262265602621351,
            "median_congestion": 0.359188,
            "max_congestion": 1.255759,
            "path_stretch": 1.7457770385479676,
            "fortz_thorup_sum": 5164
        },
        {
            "failed_links#": 2,
            "delivered_packet_rate": 0.9498163065559693,
            "median_congestion": 0.362943,
            "max_congestion": 0.961529,
            "path_stretch": 1.9007226191417002,
            "fortz_thorup_sum": 678
        },
        {
            "failed_links#": 2,
            "delivered_packet_rate": 0.88047930116311,
            "median_congestion": 0.44554,
            "max_congestion": 0.716186,
            "path_stretch": 1.9799968206745981,
            "fortz_thorup_sum": 168
        },
        {
            "failed_links#": 2,
            "delivered_packet_rate": 0.9563727876567683,
            "median_congestion": 0.387822,
            "max_congestion": 0.878829,
            "path_stretch": 1.8393402548498397,
            "fortz_thorup_sum": 219
        },
        {
            "failed_links#": 2,
            "delivered_packet_rate": 0.9387235147304478,
            "median_congestion": 0.393414,
            "max_congestion": 0.968012,
            "path_stretch": 1.9892949428991884,
            "fortz_thorup_sum": 687
        },
        {
            "failed_links#": 2,
            "delivered_packet_rate": 0.9354302306880723,
            "median_congestion": 0.374665,
            "max_congestion": 0.908818,
            "path_stretch": 1.8939454727555265,
            "fortz_thorup_sum": 710
        },
        {
            "failed_links#": 2,
            "delivered_packet_rate": 0.958837904202733,
            "median_congestion": 0.424028,
            "max_congestion": 0.903922,
            "path_stretch": 1.935072898886475,
            "fortz_thorup_sum": 681
        },
        {
            "failed_links#": 2,
            "delivered_packet_rate": 0.9549236496255954,
            "median_congestion": 0.390559,
            "max_congestion": 0.76642,
            "path_stretch": 1.8748153282055615,
            "fortz_thorup_sum": 171
        },
        {
            "failed_links#": 2,
            "delivered_packet_rate": 0.9345918274136158,
            "median_congestion": 0.3736,
            "max_congestion": 0.831262,
            "path_stretch": 1.827039629534551,
            "fortz_thorup_sum": 167
        },
        {
            "failed_links#": 2,
            "delivered_packet_rate": 0.9327697038339657,
            "median_congestion": 0.353487,
            "max_congestion": 1.005348,
            "path_stretch": 1.847825392375812,
            "fortz_thorup_sum": 693
        },
        {
            "failed_links#": 2,
            "delivered_packet_rate": 0.9575343933773895,
            "median_congestion": 0.382628,
            "max_congestion": 0.957433,
            "path_stretch": 1.771712521262022,
            "fortz_thorup_sum": 670
        },
        {
            "failed_links#": 2,
            "delivered_packet_rate": 0.9834972893023247,
            "median_congestion": 0.342512,
            "max_congestion": 0.991016,
            "path_stretch": 1.794277411464242,
            "fortz_thorup_sum": 723
        },
        {
            "failed_links#": 2,
            "delivered_packet_rate": 0.9199013146926375,
            "median_congestion": 0.373702,
            "max_congestion": 0.954095,
            "path_stretch": 1.6666592213447253,
            "fortz_thorup_sum": 641
        },
        {
            "failed_links#": 2,
            "delivered_packet_rate": 0.9899017846079022,
            "median_congestion": 0.417016,
            "max_congestion": 0.990713,
            "path_stretch": 2.0416217651507624,
            "fortz_thorup_sum": 1225
        },
        {
            "failed_links#": 2,
            "delivered_packet_rate": 0.9533946415081581,
            "median_congestion": 0.37354,
            "max_congestion": 0.937943,
            "path_stretch": 1.7341327040003456,
            "fortz_thorup_sum": 1658
        },
        {
            "failed_links#": 2,
            "delivered_packet_rate": 0.9215461732070445,
            "median_congestion": 0.378417,
            "max_congestion": 0.813206,
            "path_stretch": 1.8751196055223769,
            "fortz_thorup_sum": 167
        },
        {
            "failed_links#": 2,
            "delivered_packet_rate": 0.9211533364526608,
            "median_congestion": 0.375962,
            "max_congestion": 1.091096,
            "path_stretch": 1.8968230837136921,
            "fortz_thorup_sum": 690
        },
        {
            "failed_links#": 2,
            "delivered_packet_rate": 0.9016983792265815,
            "median_congestion": 0.441417,
            "max_congestion": 0.733645,
            "path_stretch": 1.9476618465088613,
            "fortz_thorup_sum": 196
        },
        {
            "failed_links#": 2,
            "delivered_packet_rate": 0.9418959855743768,
            "median_congestion": 0.445811,
            "max_congestion": 0.956209,
            "path_stretch": 2.085204046069491,
            "fortz_thorup_sum": 667
        },
        {
            "failed_links#": 2,
            "delivered_packet_rate": 0.9762982804978496,
            "median_congestion": 0.358844,
            "max_congestion": 1.072015,
            "path_stretch": 1.8128422181990147,
            "fortz_thorup_sum": 666
        },
        {
            "failed_links#": 2,
            "delivered_packet_rate": 0.9834972893023247,
            "median_congestion": 0.360665,
            "max_congestion": 0.87924,
            "path_stretch": 1.7934321307589516,
            "fortz_thorup_sum": 193
        },
        {
            "failed_links#": 2,
            "delivered_packet_rate": 0.9213236225783273,
            "median_congestion": 0.327833,
            "max_congestion": 0.814886,
            "path_stretch": 1.925722390703088,
            "fortz_thorup_sum": 180
        },
        {
            "failed_links#": 2,
            "delivered_packet_rate": 0.9897558472269804,
            "median_congestion": 0.426733,
            "max_congestion": 0.930298,
            "path_stretch": 2.0700552096389426,
            "fortz_thorup_sum": 714
        },
        {
            "failed_links#": 2,
            "delivered_packet_rate": 0.9646000268921805,
            "median_congestion": 0.402943,
            "max_congestion": 1.18295,
            "path_stretch": 1.8688938460665308,
            "fortz_thorup_sum": 5688
        },
        {
            "failed_links#": 2,
            "delivered_packet_rate": 0.9445720211830978,
            "median_congestion": 0.42419,
            "max_congestion": 1.248601,
            "path_stretch": 1.9228137319756282,
            "fortz_thorup_sum": 10202
        },
        {
            "failed_links#": 2,
            "delivered_packet_rate": 0.9276102513488351,
            "median_congestion": 0.433983,
            "max_congestion": 0.990713,
            "path_stretch": 2.0047544134369377,
            "fortz_thorup_sum": 1191
        },
        {
            "failed_links#": 2,
            "delivered_packet_rate": 0.9370107278708294,
            "median_congestion": 0.362929,
            "max_congestion": 0.852238,
            "path_stretch": 1.7363704793270285,
            "fortz_thorup_sum": 170
        },
        {
            "failed_links#": 2,
            "delivered_packet_rate": 0.9841190352748175,
            "median_congestion": 0.403887,
            "max_congestion": 0.961529,
            "path_stretch": 1.866946018989728,
            "fortz_thorup_sum": 682
        },
        {
            "failed_links#": 2,
            "delivered_packet_rate": 0.9137990850144952,
            "median_congestion": 0.42419,
            "max_congestion": 0.995631,
            "path_stretch": 1.8657805922569295,
            "fortz_thorup_sum": 1180
        },
        {
            "failed_links#": 2,
            "delivered_packet_rate": 0.9643078419552445,
            "median_congestion": 0.36836,
            "max_congestion": 1.036671,
            "path_stretch": 1.6275190906665333,
            "fortz_thorup_sum": 666
        },
        {
            "failed_links#": 2,
            "delivered_packet_rate": 0.9841190352748175,
            "median_congestion": 0.358844,
            "max_congestion": 0.961529,
            "path_stretch": 1.837023744592882,
            "fortz_thorup_sum": 656
        },
        {
            "failed_links#": 2,
            "delivered_packet_rate": 0.9665786338058903,
            "median_congestion": 0.357355,
            "max_congestion": 0.974993,
            "path_stretch": 1.7323907644335608,
            "fortz_thorup_sum": 672
        },
        {
            "failed_links#": 2,
            "delivered_packet_rate": 0.9111275469446125,
            "median_congestion": 0.323864,
            "max_congestion": 0.822164,
            "path_stretch": 1.705775632161369,
            "fortz_thorup_sum": 180
        },
        {
            "failed_links#": 2,
            "delivered_packet_rate": 0.9613724999693702,
            "median_congestion": 0.360665,
            "max_congestion": 0.76984,
            "path_stretch": 1.7503463516603424,
            "fortz_thorup_sum": 210
        },
        {
            "failed_links#": 2,
            "delivered_packet_rate": 1.0,
            "median_congestion": 0.374957,
            "max_congestion": 0.760011,
            "path_stretch": 1.7800993547686033,
            "fortz_thorup_sum": 165
        },
        {
            "failed_links#": 2,
            "delivered_packet_rate": 0.9897558472269804,
            "median_congestion": 0.360665,
            "max_congestion": 0.832327,
            "path_stretch": 1.839986966298684,
            "fortz_thorup_sum": 189
        },
        {
            "failed_links#": 2,
            "delivered_packet_rate": 0.8978008741044275,
            "median_congestion": 0.405807,
            "max_congestion": 0.809191,
            "path_stretch": 1.9576120825138184,
            "fortz_thorup_sum": 164
        },
        {
            "failed_links#": 2,
            "delivered_packet_rate": 0.9841190352748175,
            "median_congestion": 0.348393,
            "max_congestion": 1.017643,
            "path_stretch": 1.8949717474860288,
            "fortz_thorup_sum": 1161
        },
        {
            "failed_links#": 2,
            "delivered_packet_rate": 0.989303146679785,
            "median_congestion": 0.433885,
            "max_congestion": 0.806516,
            "path_stretch": 1.888821661333018,
            "fortz_thorup_sum": 187
        },
        {
            "failed_links#": 2,
            "delivered_packet_rate": 0.9549236496255954,
            "median_congestion": 0.390559,
            "max_congestion": 0.76642,
            "path_stretch": 1.8709950378844478,
            "fortz_thorup_sum": 157
        },
        {
            "failed_links#": 2,
            "delivered_packet_rate": 0.9709823446786594,
            "median_congestion": 0.317932,
            "max_congestion": 1.037715,
            "path_stretch": 1.6891138941481898,
            "fortz_thorup_sum": 2154
        },
        {
            "failed_links#": 2,
            "delivered_packet_rate": 0.992437931250001,
            "median_congestion": 0.446056,
            "max_congestion": 1.07825,
            "path_stretch": 2.137955976135183,
            "fortz_thorup_sum": 724
        },
        {
            "failed_links#": 2,
            "delivered_packet_rate": 0.9523881233336813,
            "median_congestion": 0.342458,
            "max_congestion": 0.933152,
            "path_stretch": 1.6744284169392756,
            "fortz_thorup_sum": 1171
        },
        {
            "failed_links#": 2,
            "delivered_packet_rate": 0.9345679439315097,
            "median_congestion": 0.44554,
            "max_congestion": 0.849467,
            "path_stretch": 1.9813128557426705,
            "fortz_thorup_sum": 192
        },
        {
            "failed_links#": 2,
            "delivered_packet_rate": 0.9537826705486113,
            "median_congestion": 0.374957,
            "max_congestion": 0.85839,
            "path_stretch": 1.8751186578954484,
            "fortz_thorup_sum": 166
        },
        {
            "failed_links#": 2,
            "delivered_packet_rate": 0.88047930116311,
            "median_congestion": 0.44554,
            "max_congestion": 0.716186,
            "path_stretch": 1.9799968206745981,
            "fortz_thorup_sum": 168
        },
        {
            "failed_links#": 2,
            "delivered_packet_rate": 0.9593796250014152,
            "median_congestion": 0.348906,
            "max_congestion": 0.961529,
            "path_stretch": 1.795775727933314,
            "fortz_thorup_sum": 653
        },
        {
            "failed_links#": 2,
            "delivered_packet_rate": 0.9834972893023247,
            "median_congestion": 0.360665,
            "max_congestion": 0.87924,
            "path_stretch": 1.7766392386187082,
            "fortz_thorup_sum": 193
        },
        {
            "failed_links#": 2,
            "delivered_packet_rate": 0.946167716945377,
            "median_congestion": 0.44554,
            "max_congestion": 0.849467,
            "path_stretch": 1.9796757846131687,
            "fortz_thorup_sum": 178
        },
        {
            "failed_links#": 2,
            "delivered_packet_rate": 0.9249062999818082,
            "median_congestion": 0.355524,
            "max_congestion": 0.971528,
            "path_stretch": 1.7002155208672005,
            "fortz_thorup_sum": 676
        },
        {
            "failed_links#": 2,
            "delivered_packet_rate": 0.9227967991791526,
            "median_congestion": 0.387619,
            "max_congestion": 0.861061,
            "path_stretch": 1.844163670812377,
            "fortz_thorup_sum": 197
        },
        {
            "failed_links#": 2,
            "delivered_packet_rate": 0.9260843449823208,
            "median_congestion": 0.374957,
            "max_congestion": 0.908818,
            "path_stretch": 1.8184380706923793,
            "fortz_thorup_sum": 648
        },
        {
            "failed_links#": 2,
            "delivered_packet_rate": 0.9445974555406654,
            "median_congestion": 0.423277,
            "max_congestion": 0.778263,
            "path_stretch": 1.827628667926394,
            "fortz_thorup_sum": 178
        },
        {
            "failed_links#": 2,
            "delivered_packet_rate": 1.0,
            "median_congestion": 0.374957,
            "max_congestion": 0.760011,
            "path_stretch": 1.7800993547686033,
            "fortz_thorup_sum": 165
        },
        {
            "failed_links#": 2,
            "delivered_packet_rate": 0.992437931250001,
            "median_congestion": 0.362577,
            "max_congestion": 0.951687,
            "path_stretch": 1.8851454134996748,
            "fortz_thorup_sum": 675
        },
        {
            "failed_links#": 2,
            "delivered_packet_rate": 0.9122187429192842,
            "median_congestion": 0.3736,
            "max_congestion": 0.911979,
            "path_stretch": 1.8302822046846066,
            "fortz_thorup_sum": 678
        },
        {
            "failed_links#": 2,
            "delivered_packet_rate": 0.9451213412715411,
            "median_congestion": 0.357355,
            "max_congestion": 0.727148,
            "path_stretch": 1.8250183195864642,
            "fortz_thorup_sum": 154
        },
        {
            "failed_links#": 2,
            "delivered_packet_rate": 0.9630558201952211,
            "median_congestion": 0.410798,
            "max_congestion": 1.005173,
            "path_stretch": 1.9189690115575124,
            "fortz_thorup_sum": 1694
        },
        {
            "failed_links#": 2,
            "delivered_packet_rate": 0.9897558472269804,
            "median_congestion": 0.426733,
            "max_congestion": 0.930298,
            "path_stretch": 2.0700552096389426,
            "fortz_thorup_sum": 714
        },
        {
            "failed_links#": 2,
            "delivered_packet_rate": 0.9834972893023247,
            "median_congestion": 0.360665,
            "max_congestion": 0.87924,
            "path_stretch": 1.7766392386187082,
            "fortz_thorup_sum": 193
        },
        {
            "failed_links#": 2,
            "delivered_packet_rate": 0.9364234113335808,
            "median_congestion": 0.351523,
            "max_congestion": 0.884725,
            "path_stretch": 1.8383418148510111,
            "fortz_thorup_sum": 167
        },
        {
            "failed_links#": 2,
            "delivered_packet_rate": 0.9647396056837104,
            "median_congestion": 0.362577,
            "max_congestion": 0.983679,
            "path_stretch": 1.8857513372610277,
            "fortz_thorup_sum": 1671
        },
        {
            "failed_links#": 2,
            "delivered_packet_rate": 0.992437931250001,
            "median_congestion": 0.362577,
            "max_congestion": 0.951687,
            "path_stretch": 1.8985663909712203,
            "fortz_thorup_sum": 679
        },
        {
            "failed_links#": 2,
            "delivered_packet_rate": 0.946906709102755,
            "median_congestion": 0.355657,
            "max_congestion": 0.851043,
            "path_stretch": 1.7950194986799335,
            "fortz_thorup_sum": 165
        },
        {
            "failed_links#": 3,
            "delivered_packet_rate": 0.8789067134452062,
            "median_congestion": 0.336326,
            "max_congestion": 0.774513,
            "path_stretch": 1.741151319339858,
            "fortz_thorup_sum": 147
        },
        {
            "failed_links#": 3,
            "delivered_packet_rate": 0.974453048873824,
            "median_congestion": 0.43335,
            "max_congestion": 0.855012,
            "path_stretch": 1.9259865324366632,
            "fortz_thorup_sum": 201
        },
        {
            "failed_links#": 3,
            "delivered_packet_rate": 0.9160363779551738,
            "median_congestion": 0.303863,
            "max_congestion": 0.900776,
            "path_stretch": 1.8625687566987483,
            "fortz_thorup_sum": 647
        },
        {
            "failed_links#": 3,
            "delivered_packet_rate": 0.9288585510077512,
            "median_congestion": 0.404739,
            "max_congestion": 0.931011,
            "path_stretch": 1.956310216538412,
            "fortz_thorup_sum": 703
        },
        {
            "failed_links#": 3,
            "delivered_packet_rate": 0.9402871073706752,
            "median_congestion": 0.372967,
            "max_congestion": 0.874507,
            "path_stretch": 1.8033416934083506,
            "fortz_thorup_sum": 214
        },
        {
            "failed_links#": 3,
            "delivered_packet_rate": 0.9225367173642686,
            "median_congestion": 0.390977,
            "max_congestion": 0.814168,
            "path_stretch": 1.903711511340733,
            "fortz_thorup_sum": 169
        },
        {
            "failed_links#": 3,
            "delivered_packet_rate": 0.9130444290149567,
            "median_congestion": 0.404671,
            "max_congestion": 0.978717,
            "path_stretch": 1.8384920590434117,
            "fortz_thorup_sum": 1152
        },
        {
            "failed_links#": 3,
            "delivered_packet_rate": 0.9171350181320604,
            "median_congestion": 0.423606,
            "max_congestion": 1.009886,
            "path_stretch": 2.044641843348,
            "fortz_thorup_sum": 1176
        },
        {
            "failed_links#": 3,
            "delivered_packet_rate": 0.953000253878313,
            "median_congestion": 0.378907,
            "max_congestion": 1.18295,
            "path_stretch": 1.8947249580873173,
            "fortz_thorup_sum": 5695
        },
        {
            "failed_links#": 3,
            "delivered_packet_rate": 0.9773918027857135,
            "median_congestion": 0.417122,
            "max_congestion": 0.853494,
            "path_stretch": 1.9599839119519329,
            "fortz_thorup_sum": 235
        },
        {
            "failed_links#": 3,
            "delivered_packet_rate": 0.9460225550021859,
            "median_congestion": 0.324109,
            "max_congestion": 0.831262,
            "path_stretch": 1.7598521003916001,
            "fortz_thorup_sum": 173
        },
        {
            "failed_links#": 3,
            "delivered_packet_rate": 0.9332714120457427,
            "median_congestion": 0.371601,
            "max_congestion": 0.87603,
            "path_stretch": 1.7287834302999467,
            "fortz_thorup_sum": 169
        },
        {
            "failed_links#": 3,
            "delivered_packet_rate": 0.8698789122965969,
            "median_congestion": 0.386119,
            "max_congestion": 0.967949,
            "path_stretch": 1.868552007158894,
            "fortz_thorup_sum": 653
        },
        {
            "failed_links#": 3,
            "delivered_packet_rate": 0.8978008741044275,
            "median_congestion": 0.427468,
            "max_congestion": 0.9464,
            "path_stretch": 1.9503364862127455,
            "fortz_thorup_sum": 682
        },
        {
            "failed_links#": 3,
            "delivered_packet_rate": 0.935381533198583,
            "median_congestion": 0.437793,
            "max_congestion": 0.951853,
            "path_stretch": 1.875602009601116,
            "fortz_thorup_sum": 1216
        },
        {
            "failed_links#": 3,
            "delivered_packet_rate": 0.8646667300457772,
            "median_congestion": 0.40445,
            "max_congestion": 0.767705,
            "path_stretch": 1.9750057344294993,
            "fortz_thorup_sum": 162
        },
        {
            "failed_links#": 3,
            "delivered_packet_rate": 0.9446794968525758,
            "median_congestion": 0.356148,
            "max_congestion": 0.88169,
            "path_stretch": 1.847988904660104,
            "fortz_thorup_sum": 189
        },
        {
            "failed_links#": 3,
            "delivered_packet_rate": 0.9177939851156278,
            "median_congestion": 0.373702,
            "max_congestion": 1.375806,
            "path_stretch": 1.7921083922266012,
            "fortz_thorup_sum": 5189
        },
        {
            "failed_links#": 3,
            "delivered_packet_rate": 0.9326640892150414,
            "median_congestion": 0.374957,
            "max_congestion": 0.973164,
            "path_stretch": 1.9529264263867279,
            "fortz_thorup_sum": 724
        },
        {
            "failed_links#": 3,
            "delivered_packet_rate": 0.8567383445117852,
            "median_congestion": 0.382231,
            "max_congestion": 1.164264,
            "path_stretch": 1.8918492835675502,
            "fortz_thorup_sum": 10175
        },
        {
            "failed_links#": 3,
            "delivered_packet_rate": 0.897843213004525,
            "median_congestion": 0.405243,
            "max_congestion": 0.950548,
            "path_stretch": 2.1110338925463275,
            "fortz_thorup_sum": 691
        },
        {
            "failed_links#": 3,
            "delivered_packet_rate": 0.9834972893023247,
            "median_congestion": 0.400366,
            "max_congestion": 1.022309,
            "path_stretch": 2.053993553428424,
            "fortz_thorup_sum": 1701
        },
        {
            "failed_links#": 3,
            "delivered_packet_rate": 0.9470099974084871,
            "median_congestion": 0.31608,
            "max_congestion": 0.923884,
            "path_stretch": 1.568937840028312,
            "fortz_thorup_sum": 1151
        },
        {
            "failed_links#": 3,
            "delivered_packet_rate": 0.9326640892150414,
            "median_congestion": 0.374957,
            "max_congestion": 0.973164,
            "path_stretch": 1.945123583443455,
            "fortz_thorup_sum": 724
        },
        {
            "failed_links#": 3,
            "delivered_packet_rate": 0.9004713265614873,
            "median_congestion": 0.367162,
            "max_congestion": 0.959714,
            "path_stretch": 1.890627993381113,
            "fortz_thorup_sum": 707
        },
        {
            "failed_links#": 3,
            "delivered_packet_rate": 0.9069268456697464,
            "median_congestion": 0.309251,
            "max_congestion": 0.915835,
            "path_stretch": 1.6056020675219347,
            "fortz_thorup_sum": 650
        },
        {
            "failed_links#": 3,
            "delivered_packet_rate": 0.9065298215516168,
            "median_congestion": 0.367433,
            "max_congestion": 1.134024,
            "path_stretch": 1.769799200882034,
            "fortz_thorup_sum": 6702
        },
        {
            "failed_links#": 3,
            "delivered_packet_rate": 0.8978008741044275,
            "median_congestion": 0.376567,
            "max_congestion": 0.930306,
            "path_stretch": 1.9794587597315412,
            "fortz_thorup_sum": 719
        },
        {
            "failed_links#": 3,
            "delivered_packet_rate": 0.957349063759747,
            "median_congestion": 0.35657,
            "max_congestion": 1.384478,
            "path_stretch": 1.8593935717592378,
            "fortz_thorup_sum": 5701
        },
        {
            "failed_links#": 3,
            "delivered_packet_rate": 0.8410096757569164,
            "median_congestion": 0.30018,
            "max_congestion": 1.048818,
            "path_stretch": 1.9157465987166054,
            "fortz_thorup_sum": 2147
        },
        {
            "failed_links#": 3,
            "delivered_packet_rate": 0.9316518328013572,
            "median_congestion": 0.427179,
            "max_congestion": 0.887308,
            "path_stretch": 2.160270288326488,
            "fortz_thorup_sum": 219
        },
        {
            "failed_links#": 3,
            "delivered_packet_rate": 0.9091706522873629,
            "median_congestion": 0.449709,
            "max_congestion": 0.838976,
            "path_stretch": 2.0604747204712046,
            "fortz_thorup_sum": 180
        },
        {
            "failed_links#": 3,
            "delivered_packet_rate": 0.8856505403017476,
            "median_congestion": 0.427468,
            "max_congestion": 0.956209,
            "path_stretch": 1.9734175747800295,
            "fortz_thorup_sum": 658
        },
        {
            "failed_links#": 3,
            "delivered_packet_rate": 0.9499991547728736,
            "median_congestion": 0.403887,
            "max_congestion": 1.002758,
            "path_stretch": 1.918564452890647,
            "fortz_thorup_sum": 2162
        },
        {
            "failed_links#": 3,
            "delivered_packet_rate": 0.9276302576422878,
            "median_congestion": 0.366798,
            "max_congestion": 0.9464,
            "path_stretch": 1.7307253890283876,
            "fortz_thorup_sum": 676
        },
        {
            "failed_links#": 3,
            "delivered_packet_rate": 0.9237933917506763,
            "median_congestion": 0.3736,
            "max_congestion": 1.024928,
            "path_stretch": 1.959476784799633,
            "fortz_thorup_sum": 2176
        },
        {
            "failed_links#": 3,
            "delivered_packet_rate": 0.9529997886156746,
            "median_congestion": 0.446975,
            "max_congestion": 0.928289,
            "path_stretch": 1.9488588694880238,
            "fortz_thorup_sum": 1163
        },
        {
            "failed_links#": 3,
            "delivered_packet_rate": 0.9000449908971365,
            "median_congestion": 0.385345,
            "max_congestion": 0.720931,
            "path_stretch": 1.906723711332864,
            "fortz_thorup_sum": 153
        },
        {
            "failed_links#": 3,
            "delivered_packet_rate": 0.883185423755783,
            "median_congestion": 0.341147,
            "max_congestion": 0.846231,
            "path_stretch": 1.9403565632510202,
            "fortz_thorup_sum": 170
        },
        {
            "failed_links#": 3,
            "delivered_packet_rate": 0.9354708636251621,
            "median_congestion": 0.438748,
            "max_congestion": 0.959953,
            "path_stretch": 1.9862126828483306,
            "fortz_thorup_sum": 678
        },
        {
            "failed_links#": 3,
            "delivered_packet_rate": 0.9307653523875961,
            "median_congestion": 0.335982,
            "max_congestion": 0.810641,
            "path_stretch": 1.9490673572884867,
            "fortz_thorup_sum": 189
        },
        {
            "failed_links#": 3,
            "delivered_packet_rate": 0.9085915553900599,
            "median_congestion": 0.346707,
            "max_congestion": 0.852067,
            "path_stretch": 1.7805628288486224,
            "fortz_thorup_sum": 161
        },
        {
            "failed_links#": 3,
            "delivered_packet_rate": 0.9009108446672605,
            "median_congestion": 0.318619,
            "max_congestion": 1.072015,
            "path_stretch": 1.7748435328548724,
            "fortz_thorup_sum": 647
        },
        {
            "failed_links#": 3,
            "delivered_packet_rate": 0.9145956146514927,
            "median_congestion": 0.348421,
            "max_congestion": 0.975918,
            "path_stretch": 1.7027180836518132,
            "fortz_thorup_sum": 637
        },
        {
            "failed_links#": 3,
            "delivered_packet_rate": 0.8944958034085451,
            "median_congestion": 0.378417,
            "max_congestion": 0.813206,
            "path_stretch": 1.8726640316397416,
            "fortz_thorup_sum": 167
        },
        {
            "failed_links#": 3,
            "delivered_packet_rate": 0.8482131821002297,
            "median_congestion": 0.323436,
            "max_congestion": 0.753073,
            "path_stretch": 1.8977044592849233,
            "fortz_thorup_sum": 157
        },
        {
            "failed_links#": 3,
            "delivered_packet_rate": 0.8181226311346623,
            "median_congestion": 0.319264,
            "max_congestion": 0.927503,
            "path_stretch": 2.0171618993240927,
            "fortz_thorup_sum": 1650
        },
        {
            "failed_links#": 3,
            "delivered_packet_rate": 0.86967605778624,
            "median_congestion": 0.39385,
            "max_congestion": 1.022794,
            "path_stretch": 2.0504079340956975,
            "fortz_thorup_sum": 1189
        },
        {
            "failed_links#": 3,
            "delivered_packet_rate": 0.9386748172409585,
            "median_congestion": 0.376567,
            "max_congestion": 0.83451,
            "path_stretch": 1.8341755650048621,
            "fortz_thorup_sum": 177
        },
        {
            "failed_links#": 3,
            "delivered_packet_rate": 0.9262265602621351,
            "median_congestion": 0.335764,
            "max_congestion": 1.255759,
            "path_stretch": 1.7040824289051766,
            "fortz_thorup_sum": 5186
        },
        {
            "failed_links#": 3,
            "delivered_packet_rate": 0.8909187091567254,
            "median_congestion": 0.38218,
            "max_congestion": 0.953294,
            "path_stretch": 1.8987430960016258,
            "fortz_thorup_sum": 683
        },
        {
            "failed_links#": 3,
            "delivered_packet_rate": 0.8830205656942316,
            "median_congestion": 0.292818,
            "max_congestion": 1.053618,
            "path_stretch": 1.7836321260379835,
            "fortz_thorup_sum": 626
        },
        {
            "failed_links#": 3,
            "delivered_packet_rate": 0.9068696183652191,
            "median_congestion": 0.427468,
            "max_congestion": 1.010754,
            "path_stretch": 1.9494116428834427,
            "fortz_thorup_sum": 695
        },
        {
            "failed_links#": 3,
            "delivered_packet_rate": 0.8575054075150151,
            "median_congestion": 0.351523,
            "max_congestion": 1.095929,
            "path_stretch": 1.8851895703453978,
            "fortz_thorup_sum": 648
        },
        {
            "failed_links#": 3,
            "delivered_packet_rate": 0.957349063759747,
            "median_congestion": 0.35657,
            "max_congestion": 1.384478,
            "path_stretch": 1.8593935717592378,
            "fortz_thorup_sum": 5701
        },
        {
            "failed_links#": 3,
            "delivered_packet_rate": 0.9652672135156936,
            "median_congestion": 0.446975,
            "max_congestion": 1.081613,
            "path_stretch": 2.0349164459490114,
            "fortz_thorup_sum": 1715
        },
        {
            "failed_links#": 3,
            "delivered_packet_rate": 0.8678502121054825,
            "median_congestion": 0.412019,
            "max_congestion": 0.860065,
            "path_stretch": 1.8941224988487049,
            "fortz_thorup_sum": 190
        },
        {
            "failed_links#": 3,
            "delivered_packet_rate": 0.9045518349880916,
            "median_congestion": 0.43032,
            "max_congestion": 0.806516,
            "path_stretch": 1.9460193644499442,
            "fortz_thorup_sum": 174
        },
        {
            "failed_links#": 3,
            "delivered_packet_rate": 0.8592409922439167,
            "median_congestion": 0.293095,
            "max_congestion": 0.666657,
            "path_stretch": 1.774525946955442,
            "fortz_thorup_sum": 124
        },
        {
            "failed_links#": 3,
            "delivered_packet_rate": 0.8578144969944809,
            "median_congestion": 0.318619,
            "max_congestion": 0.758835,
            "path_stretch": 1.7526955542622773,
            "fortz_thorup_sum": 166
        },
        {
            "failed_links#": 3,
            "delivered_packet_rate": 0.974453048873824,
            "median_congestion": 0.422029,
            "max_congestion": 0.855012,
            "path_stretch": 1.915819347062439,
            "fortz_thorup_sum": 211
        },
        {
            "failed_links#": 3,
            "delivered_packet_rate": 0.9383720863508846,
            "median_congestion": 0.486047,
            "max_congestion": 0.918695,
            "path_stretch": 1.901051339956152,
            "fortz_thorup_sum": 696
        },
        {
            "failed_links#": 3,
            "delivered_packet_rate": 0.930878101033643,
            "median_congestion": 0.357355,
            "max_congestion": 1.267565,
            "path_stretch": 1.843573992083557,
            "fortz_thorup_sum": 10694
        },
        {
            "failed_links#": 3,
            "delivered_packet_rate": 0.8591943108925273,
            "median_congestion": 0.382649,
            "max_congestion": 0.895567,
            "path_stretch": 2.0268784393430153,
            "fortz_thorup_sum": 162
        },
        {
            "failed_links#": 3,
            "delivered_packet_rate": 0.8489321679641549,
            "median_congestion": 0.342458,
            "max_congestion": 1.069678,
            "path_stretch": 1.7681725336095535,
            "fortz_thorup_sum": 630
        },
        {
            "failed_links#": 3,
            "delivered_packet_rate": 0.9160104783349677,
            "median_congestion": 0.372967,
            "max_congestion": 0.990713,
            "path_stretch": 1.9354583470260864,
            "fortz_thorup_sum": 1191
        },
        {
            "failed_links#": 3,
            "delivered_packet_rate": 0.981226497451679,
            "median_congestion": 0.39101,
            "max_congestion": 1.036671,
            "path_stretch": 1.6897236991564093,
            "fortz_thorup_sum": 689
        },
        {
            "failed_links#": 3,
            "delivered_packet_rate": 0.9629145354406836,
            "median_congestion": 0.414954,
            "max_congestion": 0.957433,
            "path_stretch": 1.887190897287123,
            "fortz_thorup_sum": 2678
        },
        {
            "failed_links#": 3,
            "delivered_packet_rate": 0.8991271827990541,
            "median_congestion": 0.458963,
            "max_congestion": 1.264708,
            "path_stretch": 1.9277044129245948,
            "fortz_thorup_sum": 5664
        },
        {
            "failed_links#": 3,
            "delivered_packet_rate": 0.9633129553467285,
            "median_congestion": 0.433388,
            "max_congestion": 1.131482,
            "path_stretch": 1.866862816314181,
            "fortz_thorup_sum": 6665
        },
        {
            "failed_links#": 3,
            "delivered_packet_rate": 0.9899017846079022,
            "median_congestion": 0.374957,
            "max_congestion": 0.918695,
            "path_stretch": 1.821949945202186,
            "fortz_thorup_sum": 685
        },
        {
            "failed_links#": 3,
            "delivered_packet_rate": 0.8127376813574378,
            "median_congestion": 0.30018,
            "max_congestion": 0.815036,
            "path_stretch": 1.714990121506645,
            "fortz_thorup_sum": 141
        },
        {
            "failed_links#": 3,
            "delivered_packet_rate": 0.9608890920880382,
            "median_congestion": 0.446975,
            "max_congestion": 0.928289,
            "path_stretch": 1.9427446939061532,
            "fortz_thorup_sum": 1165
        },
        {
            "failed_links#": 3,
            "delivered_packet_rate": 0.9200005707221698,
            "median_congestion": 0.415646,
            "max_congestion": 1.063437,
            "path_stretch": 1.8468741482281374,
            "fortz_thorup_sum": 683
        },
        {
            "failed_links#": 3,
            "delivered_packet_rate": 0.8360059311681147,
            "median_congestion": 0.295549,
            "max_congestion": 0.803409,
            "path_stretch": 1.8778525115532594,
            "fortz_thorup_sum": 132
        },
        {
            "failed_links#": 3,
            "delivered_packet_rate": 0.8827089948140275,
            "median_congestion": 0.34187,
            "max_congestion": 0.976814,
            "path_stretch": 1.8519802113563852,
            "fortz_thorup_sum": 1136
        },
        {
            "failed_links#": 3,
            "delivered_packet_rate": 0.953813532970294,
            "median_congestion": 0.452501,
            "max_congestion": 1.021128,
            "path_stretch": 1.9596135001538717,
            "fortz_thorup_sum": 1212
        },
        {
            "failed_links#": 3,
            "delivered_packet_rate": 0.9050692070420292,
            "median_congestion": 0.374957,
            "max_congestion": 0.753073,
            "path_stretch": 1.7302132912878714,
            "fortz_thorup_sum": 146
        },
        {
            "failed_links#": 3,
            "delivered_packet_rate": 0.8592409922439167,
            "median_congestion": 0.344519,
            "max_congestion": 0.902869,
            "path_stretch": 1.8118408289038688,
            "fortz_thorup_sum": 644
        },
        {
            "failed_links#": 3,
            "delivered_packet_rate": 0.9571117798141462,
            "median_congestion": 0.360383,
            "max_congestion": 0.992144,
            "path_stretch": 1.7810798006966189,
            "fortz_thorup_sum": 681
        },
        {
            "failed_links#": 3,
            "delivered_packet_rate": 0.9246195431089873,
            "median_congestion": 0.386988,
            "max_congestion": 1.267565,
            "path_stretch": 1.8350697566108456,
            "fortz_thorup_sum": 11155
        },
        {
            "failed_links#": 3,
            "delivered_packet_rate": 0.9736113887608986,
            "median_congestion": 0.361507,
            "max_congestion": 0.957433,
            "path_stretch": 1.777448937406808,
            "fortz_thorup_sum": 666
        },
        {
            "failed_links#": 3,
            "delivered_packet_rate": 0.8595351933189526,
            "median_congestion": 0.356148,
            "max_congestion": 1.084757,
            "path_stretch": 1.89846740865065,
            "fortz_thorup_sum": 686
        },
        {
            "failed_links#": 3,
            "delivered_packet_rate": 0.8585826456105339,
            "median_congestion": 0.344217,
            "max_congestion": 0.640496,
            "path_stretch": 1.6782443211260814,
            "fortz_thorup_sum": 130
        },
        {
            "failed_links#": 3,
            "delivered_packet_rate": 0.9228760489152324,
            "median_congestion": 0.374957,
            "max_congestion": 0.810641,
            "path_stretch": 1.9468343915320803,
            "fortz_thorup_sum": 191
        },
        {
            "failed_links#": 3,
            "delivered_packet_rate": 0.8610762982649891,
            "median_congestion": 0.362577,
            "max_congestion": 0.769066,
            "path_stretch": 1.9095067236171157,
            "fortz_thorup_sum": 147
        },
        {
            "failed_links#": 3,
            "delivered_packet_rate": 0.9524182103176333,
            "median_congestion": 0.47021,
            "max_congestion": 1.021298,
            "path_stretch": 2.1189259394050914,
            "fortz_thorup_sum": 725
        },
        {
            "failed_links#": 3,
            "delivered_packet_rate": 0.9451213412715411,
            "median_congestion": 0.369097,
            "max_congestion": 0.83451,
            "path_stretch": 1.8619791142766426,
            "fortz_thorup_sum": 202
        },
        {
            "failed_links#": 3,
            "delivered_packet_rate": 0.7735279826785821,
            "median_congestion": 0.253953,
            "max_congestion": 0.682358,
            "path_stretch": 1.8441963534459331,
            "fortz_thorup_sum": 117
        },
        {
            "failed_links#": 3,
            "delivered_packet_rate": 0.8812096084179039,
            "median_congestion": 0.374957,
            "max_congestion": 0.876906,
            "path_stretch": 1.8954302412255,
            "fortz_thorup_sum": 184
        },
        {
            "failed_links#": 3,
            "delivered_packet_rate": 0.8570488297791662,
            "median_congestion": 0.378417,
            "max_congestion": 0.999314,
            "path_stretch": 1.9690777244120432,
            "fortz_thorup_sum": 1181
        },
        {
            "failed_links#": 3,
            "delivered_packet_rate": 0.9163774154691453,
            "median_congestion": 0.302519,
            "max_congestion": 0.986085,
            "path_stretch": 1.857240087835465,
            "fortz_thorup_sum": 712
        },
        {
            "failed_links#": 3,
            "delivered_packet_rate": 0.8704826681137369,
            "median_congestion": 0.346707,
            "max_congestion": 1.000486,
            "path_stretch": 1.953826673581755,
            "fortz_thorup_sum": 641
        },
        {
            "failed_links#": 3,
            "delivered_packet_rate": 0.8935204578308432,
            "median_congestion": 0.417122,
            "max_congestion": 1.077342,
            "path_stretch": 1.9247118318934615,
            "fortz_thorup_sum": 698
        },
        {
            "failed_links#": 3,
            "delivered_packet_rate": 0.9127337886600296,
            "median_congestion": 0.323554,
            "max_congestion": 0.995211,
            "path_stretch": 1.8500971378143767,
            "fortz_thorup_sum": 682
        },
        {
            "failed_links#": 3,
            "delivered_packet_rate": 0.7895035508069127,
            "median_congestion": 0.297618,
            "max_congestion": 0.739175,
            "path_stretch": 1.6947957415608697,
            "fortz_thorup_sum": 146
        },
        {
            "failed_links#": 3,
            "delivered_packet_rate": 0.9387235147304478,
            "median_congestion": 0.393414,
            "max_congestion": 0.968012,
            "path_stretch": 1.9892949428991884,
            "fortz_thorup_sum": 687
        },
        {
            "failed_links#": 3,
            "delivered_packet_rate": 0.9084065359475096,
            "median_congestion": 0.318619,
            "max_congestion": 0.834559,
            "path_stretch": 1.725736027439349,
            "fortz_thorup_sum": 180
        },
        {
            "failed_links#": 3,
            "delivered_packet_rate": 0.9228133935465901,
            "median_congestion": 0.469353,
            "max_congestion": 1.204453,
            "path_stretch": 2.201740424054422,
            "fortz_thorup_sum": 6698
        },
        {
            "failed_links#": 3,
            "delivered_packet_rate": 0.9233555796079108,
            "median_congestion": 0.33066,
            "max_congestion": 0.967949,
            "path_stretch": 1.737135638427417,
            "fortz_thorup_sum": 663
        },
        {
            "failed_links#": 4,
            "delivered_packet_rate": 0.8373497647554556,
            "median_congestion": 0.339135,
            "max_congestion": 1.071704,
            "path_stretch": 1.995846946112819,
            "fortz_thorup_sum": 667
        },
        {
            "failed_links#": 4,
            "delivered_packet_rate": 0.8504317094478248,
            "median_congestion": 0.312948,
            "max_congestion": 0.783999,
            "path_stretch": 1.7972143790799613,
            "fortz_thorup_sum": 159
        },
        {
            "failed_links#": 4,
            "delivered_packet_rate": 0.8791520619432066,
            "median_congestion": 0.37879,
            "max_congestion": 1.032003,
            "path_stretch": 1.9485935134048735,
            "fortz_thorup_sum": 680
        },
        {
            "failed_links#": 4,
            "delivered_packet_rate": 0.8109960482142367,
            "median_congestion": 0.279476,
            "max_congestion": 0.972076,
            "path_stretch": 1.7596732328363687,
            "fortz_thorup_sum": 1165
        },
        {
            "failed_links#": 4,
            "delivered_packet_rate": 0.892024793535827,
            "median_congestion": 0.328283,
            "max_congestion": 1.012888,
            "path_stretch": 1.6920526854145839,
            "fortz_thorup_sum": 1650
        },
        {
            "failed_links#": 4,
            "delivered_packet_rate": 0.830294211931164,
            "median_congestion": 0.339135,
            "max_congestion": 0.926225,
            "path_stretch": 1.9221210876940742,
            "fortz_thorup_sum": 644
        },
        {
            "failed_links#": 4,
            "delivered_packet_rate": 0.8586510392183836,
            "median_congestion": 0.342458,
            "max_congestion": 0.76642,
            "path_stretch": 1.8455672812543968,
            "fortz_thorup_sum": 168
        },
        {
            "failed_links#": 4,
            "delivered_packet_rate": 0.8929167020137032,
            "median_congestion": 0.334357,
            "max_congestion": 1.010149,
            "path_stretch": 1.7936000590070822,
            "fortz_thorup_sum": 651
        },
        {
            "failed_links#": 4,
            "delivered_packet_rate": 0.8571262184646923,
            "median_congestion": 0.3305,
            "max_congestion": 0.928289,
            "path_stretch": 1.7263509673450368,
            "fortz_thorup_sum": 670
        },
        {
            "failed_links#": 4,
            "delivered_packet_rate": 0.8708286684291849,
            "median_congestion": 0.410654,
            "max_congestion": 1.174117,
            "path_stretch": 2.0339916204191644,
            "fortz_thorup_sum": 11171
        },
        {
            "failed_links#": 4,
            "delivered_packet_rate": 0.9480644376347226,
            "median_congestion": 0.399263,
            "max_congestion": 0.957433,
            "path_stretch": 1.8841367483645484,
            "fortz_thorup_sum": 2190
        },
        {
            "failed_links#": 4,
            "delivered_packet_rate": 0.9215078665831469,
            "median_congestion": 0.329451,
            "max_congestion": 1.088297,
            "path_stretch": 1.908887408244158,
            "fortz_thorup_sum": 3160
        },
        {
            "failed_links#": 4,
            "delivered_packet_rate": 0.9375941672194246,
            "median_congestion": 0.374957,
            "max_congestion": 1.177635,
            "path_stretch": 1.8890020091813635,
            "fortz_thorup_sum": 5682
        },
        {
            "failed_links#": 4,
            "delivered_packet_rate": 0.9061434984741712,
            "median_congestion": 0.42419,
            "max_congestion": 1.097386,
            "path_stretch": 1.877313691793545,
            "fortz_thorup_sum": 1209
        },
        {
            "failed_links#": 4,
            "delivered_packet_rate": 0.8589689686879796,
            "median_congestion": 0.347515,
            "max_congestion": 0.906709,
            "path_stretch": 2.0049098266044156,
            "fortz_thorup_sum": 1663
        },
        {
            "failed_links#": 4,
            "delivered_packet_rate": 0.8404612861937499,
            "median_congestion": 0.311321,
            "max_congestion": 1.039533,
            "path_stretch": 1.887247765843001,
            "fortz_thorup_sum": 641
        },
        {
            "failed_links#": 4,
            "delivered_packet_rate": 0.8371723446026664,
            "median_congestion": 0.478711,
            "max_congestion": 1.415694,
            "path_stretch": 1.9613437326191516,
            "fortz_thorup_sum": 6187
        },
        {
            "failed_links#": 4,
            "delivered_packet_rate": 0.9652383672321107,
            "median_congestion": 0.328502,
            "max_congestion": 0.999175,
            "path_stretch": 1.8079767883511368,
            "fortz_thorup_sum": 675
        },
        {
            "failed_links#": 4,
            "delivered_packet_rate": 0.9039074462338618,
            "median_congestion": 0.410571,
            "max_congestion": 1.187559,
            "path_stretch": 1.8564137439936739,
            "fortz_thorup_sum": 10169
        },
        {
            "failed_links#": 4,
            "delivered_packet_rate": 0.8420152634061164,
            "median_congestion": 0.361507,
            "max_congestion": 1.319252,
            "path_stretch": 1.9059304439438673,
            "fortz_thorup_sum": 10184
        },
        {
            "failed_links#": 4,
            "delivered_packet_rate": 0.9226427972458313,
            "median_congestion": 0.341147,
            "max_congestion": 0.961529,
            "path_stretch": 1.828922026262245,
            "fortz_thorup_sum": 2149
        },
        {
            "failed_links#": 4,
            "delivered_packet_rate": 0.9216731899073367,
            "median_congestion": 0.297779,
            "max_congestion": 0.752683,
            "path_stretch": 1.8264348048541328,
            "fortz_thorup_sum": 194
        },
        {
            "failed_links#": 4,
            "delivered_packet_rate": 0.8717824568379727,
            "median_congestion": 0.405807,
            "max_congestion": 1.007296,
            "path_stretch": 1.867249365559744,
            "fortz_thorup_sum": 1649
        },
        {
            "failed_links#": 4,
            "delivered_packet_rate": 0.8366594700875671,
            "median_congestion": 0.3619,
            "max_congestion": 0.822859,
            "path_stretch": 1.8056371533145643,
            "fortz_thorup_sum": 147
        },
        {
            "failed_links#": 4,
            "delivered_packet_rate": 0.8114029979353194,
            "median_congestion": 0.293095,
            "max_congestion": 1.081557,
            "path_stretch": 1.6941952151198956,
            "fortz_thorup_sum": 625
        },
        {
            "failed_links#": 4,
            "delivered_packet_rate": 0.9535281718853884,
            "median_congestion": 0.373702,
            "max_congestion": 1.036671,
            "path_stretch": 1.6817400205562867,
            "fortz_thorup_sum": 694
        },
        {
            "failed_links#": 4,
            "delivered_packet_rate": 0.902651857460277,
            "median_congestion": 0.346707,
            "max_congestion": 0.962059,
            "path_stretch": 1.8791624150047026,
            "fortz_thorup_sum": 1183
        },
        {
            "failed_links#": 4,
            "delivered_packet_rate": 0.8619692923556883,
            "median_congestion": 0.303856,
            "max_congestion": 0.903524,
            "path_stretch": 1.6163096347402242,
            "fortz_thorup_sum": 650
        },
        {
            "failed_links#": 4,
            "delivered_packet_rate": 0.882171306291545,
            "median_congestion": 0.354945,
            "max_congestion": 0.833259,
            "path_stretch": 1.605309365817873,
            "fortz_thorup_sum": 170
        },
        {
            "failed_links#": 4,
            "delivered_packet_rate": 0.8730293607089734,
            "median_congestion": 0.312948,
            "max_congestion": 0.839414,
            "path_stretch": 1.729349097135424,
            "fortz_thorup_sum": 206
        },
        {
            "failed_links#": 4,
            "delivered_packet_rate": 0.8555674335383953,
            "median_congestion": 0.400697,
            "max_congestion": 0.977624,
            "path_stretch": 2.092979030481047,
            "fortz_thorup_sum": 670
        },
        {
            "failed_links#": 4,
            "delivered_packet_rate": 0.8414915327627869,
            "median_congestion": 0.312948,
            "max_congestion": 0.906856,
            "path_stretch": 1.8157668119632586,
            "fortz_thorup_sum": 663
        },
        {
            "failed_links#": 4,
            "delivered_packet_rate": 0.9355366207447273,
            "median_congestion": 0.386146,
            "max_congestion": 0.897353,
            "path_stretch": 1.8546801202125953,
            "fortz_thorup_sum": 228
        },
        {
            "failed_links#": 4,
            "delivered_packet_rate": 0.9184931197736467,
            "median_congestion": 0.362929,
            "max_congestion": 1.002859,
            "path_stretch": 1.754811301421925,
            "fortz_thorup_sum": 1190
        },
        {
            "failed_links#": 4,
            "delivered_packet_rate": 0.9003486523124872,
            "median_congestion": 0.273204,
            "max_congestion": 0.81504,
            "path_stretch": 1.7221828002626969,
            "fortz_thorup_sum": 151
        },
        {
            "failed_links#": 4,
            "delivered_packet_rate": 0.8286155443316975,
            "median_congestion": 0.39551,
            "max_congestion": 0.976163,
            "path_stretch": 1.9742876591047778,
            "fortz_thorup_sum": 696
        },
        {
            "failed_links#": 4,
            "delivered_packet_rate": 0.8712246069344914,
            "median_congestion": 0.306442,
            "max_congestion": 0.763286,
            "path_stretch": 1.883718095166213,
            "fortz_thorup_sum": 151
        },
        {
            "failed_links#": 4,
            "delivered_packet_rate": 0.862982014032011,
            "median_congestion": 0.318619,
            "max_congestion": 0.949851,
            "path_stretch": 1.6424652628704828,
            "fortz_thorup_sum": 2138
        },
        {
            "failed_links#": 4,
            "delivered_packet_rate": 0.9005206444011612,
            "median_congestion": 0.360665,
            "max_congestion": 0.972528,
            "path_stretch": 1.8358370829904003,
            "fortz_thorup_sum": 2172
        },
        {
            "failed_links#": 4,
            "delivered_packet_rate": 0.890082477107915,
            "median_congestion": 0.324237,
            "max_congestion": 0.932807,
            "path_stretch": 1.882908807447787,
            "fortz_thorup_sum": 668
        },
        {
            "failed_links#": 4,
            "delivered_packet_rate": 0.8801863407884434,
            "median_congestion": 0.3736,
            "max_congestion": 1.029876,
            "path_stretch": 1.8442824631709818,
            "fortz_thorup_sum": 676
        },
        {
            "failed_links#": 4,
            "delivered_packet_rate": 0.8633044410404451,
            "median_congestion": 0.303863,
            "max_congestion": 0.892355,
            "path_stretch": 1.8621216081547882,
            "fortz_thorup_sum": 160
        },
        {
            "failed_links#": 4,
            "delivered_packet_rate": 0.9422137599564266,
            "median_congestion": 0.431651,
            "max_congestion": 1.269942,
            "path_stretch": 2.117454012791875,
            "fortz_thorup_sum": 12201
        },
        {
            "failed_links#": 4,
            "delivered_packet_rate": 0.7985229772280303,
            "median_congestion": 0.306138,
            "max_congestion": 0.992266,
            "path_stretch": 2.0391379109094783,
            "fortz_thorup_sum": 668
        },
        {
            "failed_links#": 4,
            "delivered_packet_rate": 0.7671461301547416,
            "median_congestion": 0.246967,
            "max_congestion": 0.777963,
            "path_stretch": 1.6325082508918025,
            "fortz_thorup_sum": 118
        },
        {
            "failed_links#": 4,
            "delivered_packet_rate": 0.8773632821859776,
            "median_congestion": 0.306442,
            "max_congestion": 0.813641,
            "path_stretch": 1.7214949893760996,
            "fortz_thorup_sum": 132
        },
        {
            "failed_links#": 4,
            "delivered_packet_rate": 0.944680892640491,
            "median_congestion": 0.412177,
            "max_congestion": 1.043063,
            "path_stretch": 1.9891668438326402,
            "fortz_thorup_sum": 1193
        },
        {
            "failed_links#": 4,
            "delivered_packet_rate": 0.8642191473876045,
            "median_congestion": 0.296534,
            "max_congestion": 0.951146,
            "path_stretch": 1.8327572532298717,
            "fortz_thorup_sum": 652
        },
        {
            "failed_links#": 4,
            "delivered_packet_rate": 0.8936547636458042,
            "median_congestion": 0.437657,
            "max_congestion": 1.240118,
            "path_stretch": 1.8742653663666689,
            "fortz_thorup_sum": 10209
        },
        {
            "failed_links#": 4,
            "delivered_packet_rate": 0.8479928026971585,
            "median_congestion": 0.294185,
            "max_congestion": 1.028656,
            "path_stretch": 1.7663174088650238,
            "fortz_thorup_sum": 661
        },
        {
            "failed_links#": 4,
            "delivered_packet_rate": 0.8534853832314072,
            "median_congestion": 0.252091,
            "max_congestion": 1.092987,
            "path_stretch": 1.7798379224103187,
            "fortz_thorup_sum": 2627
        },
        {
            "failed_links#": 4,
            "delivered_packet_rate": 0.8087176570738299,
            "median_congestion": 0.302444,
            "max_congestion": 1.457015,
            "path_stretch": 1.663347797882914,
            "fortz_thorup_sum": 6165
        },
        {
            "failed_links#": 4,
            "delivered_packet_rate": 0.8359902673259542,
            "median_congestion": 0.371667,
            "max_congestion": 1.091096,
            "path_stretch": 1.870878996727726,
            "fortz_thorup_sum": 1185
        },
        {
            "failed_links#": 4,
            "delivered_packet_rate": 0.9236531926089618,
            "median_congestion": 0.444534,
            "max_congestion": 0.994645,
            "path_stretch": 1.912005249658492,
            "fortz_thorup_sum": 2193
        },
        {
            "failed_links#": 4,
            "delivered_packet_rate": 0.9265449549943695,
            "median_congestion": 0.361507,
            "max_congestion": 0.802913,
            "path_stretch": 1.7980102527450057,
            "fortz_thorup_sum": 216
        },
        {
            "failed_links#": 4,
            "delivered_packet_rate": 0.9097804565188026,
            "median_congestion": 0.264074,
            "max_congestion": 0.832327,
            "path_stretch": 1.6761033078894287,
            "fortz_thorup_sum": 165
        },
        {
            "failed_links#": 4,
            "delivered_packet_rate": 0.8896927421044543,
            "median_congestion": 0.382231,
            "max_congestion": 0.932665,
            "path_stretch": 1.9337926555967968,
            "fortz_thorup_sum": 1173
        },
        {
            "failed_links#": 4,
            "delivered_packet_rate": 0.883348730941873,
            "median_congestion": 0.329884,
            "max_congestion": 1.056326,
            "path_stretch": 1.677533060723441,
            "fortz_thorup_sum": 2173
        },
        {
            "failed_links#": 4,
            "delivered_packet_rate": 0.9035174010553088,
            "median_congestion": 0.384288,
            "max_congestion": 0.903922,
            "path_stretch": 2.021332752245422,
            "fortz_thorup_sum": 698
        },
        {
            "failed_links#": 4,
            "delivered_packet_rate": 0.8115427318143955,
            "median_congestion": 0.249069,
            "max_congestion": 0.828395,
            "path_stretch": 1.6545137686537974,
            "fortz_thorup_sum": 158
        },
        {
            "failed_links#": 4,
            "delivered_packet_rate": 0.8755126224978369,
            "median_congestion": 0.365099,
            "max_congestion": 1.337764,
            "path_stretch": 1.8876242483396157,
            "fortz_thorup_sum": 5181
        },
        {
            "failed_links#": 4,
            "delivered_packet_rate": 0.8966198824405383,
            "median_congestion": 0.326874,
            "max_congestion": 0.935625,
            "path_stretch": 1.8227520833120727,
            "fortz_thorup_sum": 661
        },
        {
            "failed_links#": 4,
            "delivered_packet_rate": 0.9218642577641866,
            "median_congestion": 0.30018,
            "max_congestion": 0.941741,
            "path_stretch": 1.8142097961571433,
            "fortz_thorup_sum": 675
        },
        {
            "failed_links#": 4,
            "delivered_packet_rate": 0.749407526801842,
            "median_congestion": 0.23422,
            "max_congestion": 0.769427,
            "path_stretch": 1.8266489837459785,
            "fortz_thorup_sum": 113
        },
        {
            "failed_links#": 4,
            "delivered_packet_rate": 0.9647237867540037,
            "median_congestion": 0.3736,
            "max_congestion": 1.036671,
            "path_stretch": 1.7371489309050872,
            "fortz_thorup_sum": 692
        },
        {
            "failed_links#": 4,
            "delivered_packet_rate": 0.8993080148778585,
            "median_congestion": 0.381797,
            "max_congestion": 0.809469,
            "path_stretch": 1.8387669566391063,
            "fortz_thorup_sum": 174
        },
        {
            "failed_links#": 4,
            "delivered_packet_rate": 0.8519189990153492,
            "median_congestion": 0.320751,
            "max_congestion": 0.986085,
            "path_stretch": 1.8570753314719841,
            "fortz_thorup_sum": 663
        },
        {
            "failed_links#": 4,
            "delivered_packet_rate": 0.8344155083824043,
            "median_congestion": 0.302663,
            "max_congestion": 1.007296,
            "path_stretch": 1.9288018309556096,
            "fortz_thorup_sum": 1128
        },
        {
            "failed_links#": 4,
            "delivered_packet_rate": 0.83545506020421,
            "median_congestion": 0.344487,
            "max_congestion": 1.057462,
            "path_stretch": 1.9406484728330047,
            "fortz_thorup_sum": 1164
        },
        {
            "failed_links#": 4,
            "delivered_packet_rate": 0.8912429972157133,
            "median_congestion": 0.309251,
            "max_congestion": 1.255759,
            "path_stretch": 1.7711690522929437,
            "fortz_thorup_sum": 6661
        },
        {
            "failed_links#": 4,
            "delivered_packet_rate": 0.9042069202854666,
            "median_congestion": 0.321317,
            "max_congestion": 0.995211,
            "path_stretch": 1.8528815183895626,
            "fortz_thorup_sum": 677
        },
        {
            "failed_links#": 4,
            "delivered_packet_rate": 0.8462930431914163,
            "median_congestion": 0.252091,
            "max_congestion": 0.914052,
            "path_stretch": 1.7024873799823939,
            "fortz_thorup_sum": 642
        },
        {
            "failed_links#": 4,
            "delivered_packet_rate": 0.919854633341248,
            "median_congestion": 0.383459,
            "max_congestion": 0.814168,
            "path_stretch": 1.819306255954994,
            "fortz_thorup_sum": 165
        },
        {
            "failed_links#": 4,
            "delivered_packet_rate": 0.7660671860962154,
            "median_congestion": 0.287254,
            "max_congestion": 1.099596,
            "path_stretch": 1.7086944994030189,
            "fortz_thorup_sum": 616
        },
        {
            "failed_links#": 4,
            "delivered_packet_rate": 0.9109619134453303,
            "median_congestion": 0.321033,
            "max_congestion": 0.81504,
            "path_stretch": 1.7911262720774905,
            "fortz_thorup_sum": 164
        },
        {
            "failed_links#": 4,
            "delivered_packet_rate": 0.9275218514475329,
            "median_congestion": 0.315567,
            "max_congestion": 0.993694,
            "path_stretch": 1.7436247199432926,
            "fortz_thorup_sum": 1186
        },
        {
            "failed_links#": 4,
            "delivered_packet_rate": 0.8089544757567924,
            "median_congestion": 0.293095,
            "max_congestion": 0.942527,
            "path_stretch": 1.694919555390682,
            "fortz_thorup_sum": 654
        },
        {
            "failed_links#": 4,
            "delivered_packet_rate": 0.7869588743497761,
            "median_congestion": 0.349298,
            "max_congestion": 0.723088,
            "path_stretch": 1.9452832265991473,
            "fortz_thorup_sum": 147
        },
        {
            "failed_links#": 4,
            "delivered_packet_rate": 0.8017191764665195,
            "median_congestion": 0.308005,
            "max_congestion": 0.882513,
            "path_stretch": 1.7021255693532518,
            "fortz_thorup_sum": 151
        },
        {
            "failed_links#": 4,
            "delivered_packet_rate": 0.8324294572664797,
            "median_congestion": 0.289519,
            "max_congestion": 1.069678,
            "path_stretch": 1.7893315411829123,
            "fortz_thorup_sum": 640
        },
        {
            "failed_links#": 4,
            "delivered_packet_rate": 0.8217130629154504,
            "median_congestion": 0.405807,
            "max_congestion": 0.827932,
            "path_stretch": 2.0376333248437692,
            "fortz_thorup_sum": 165
        },
        {
            "failed_links#": 4,
            "delivered_packet_rate": 0.8508778963180821,
            "median_congestion": 0.318619,
            "max_congestion": 0.815543,
            "path_stretch": 1.665926577836686,
            "fortz_thorup_sum": 173
        },
        {
            "failed_links#": 4,
            "delivered_packet_rate": 0.8281062368301595,
            "median_congestion": 0.404066,
            "max_congestion": 0.717658,
            "path_stretch": 1.7804148353937896,
            "fortz_thorup_sum": 150
        },
        {
            "failed_links#": 4,
            "delivered_packet_rate": 0.8429769612797576,
            "median_congestion": 0.252091,
            "max_congestion": 0.871891,
            "path_stretch": 1.8111998774965008,
            "fortz_thorup_sum": 182
        },
        {
            "failed_links#": 4,
            "delivered_packet_rate": 0.8809090487534761,
            "median_congestion": 0.373702,
            "max_congestion": 1.315053,
            "path_stretch": 1.8478795119408022,
            "fortz_thorup_sum": 5180
        },
        {
            "failed_links#": 4,
            "delivered_packet_rate": 0.9278413317925902,
            "median_congestion": 0.38779,
            "max_congestion": 0.992169,
            "path_stretch": 2.071196925108767,
            "fortz_thorup_sum": 727
        },
        {
            "failed_links#": 4,
            "delivered_packet_rate": 0.9378741002402151,
            "median_congestion": 0.428726,
            "max_congestion": 1.01692,
            "path_stretch": 1.9622303993103356,
            "fortz_thorup_sum": 2206
        },
        {
            "failed_links#": 4,
            "delivered_packet_rate": 0.8976536960231366,
            "median_congestion": 0.422029,
            "max_congestion": 0.879405,
            "path_stretch": 2.019217836074184,
            "fortz_thorup_sum": 203
        },
        {
            "failed_links#": 4,
            "delivered_packet_rate": 0.8270302394350099,
            "median_congestion": 0.378417,
            "max_congestion": 1.124519,
            "path_stretch": 2.142796406251006,
            "fortz_thorup_sum": 6669
        },
        {
            "failed_links#": 4,
            "delivered_packet_rate": 0.8865698992752914,
            "median_congestion": 0.30018,
            "max_congestion": 0.848909,
            "path_stretch": 1.7460227656048948,
            "fortz_thorup_sum": 167
        },
        {
            "failed_links#": 4,
            "delivered_packet_rate": 0.8774723087309171,
            "median_congestion": 0.291303,
            "max_congestion": 1.048126,
            "path_stretch": 1.7718770804185384,
            "fortz_thorup_sum": 697
        },
        {
            "failed_links#": 4,
            "delivered_packet_rate": 0.9483347552276522,
            "median_congestion": 0.404587,
            "max_congestion": 0.961529,
            "path_stretch": 1.9415802497805201,
            "fortz_thorup_sum": 1680
        },
        {
            "failed_links#": 4,
            "delivered_packet_rate": 0.7410483080646609,
            "median_congestion": 0.295081,
            "max_congestion": 0.84397,
            "path_stretch": 1.7628558287699552,
            "fortz_thorup_sum": 152
        },
        {
            "failed_links#": 4,
            "delivered_packet_rate": 0.8381149667081319,
            "median_congestion": 0.296163,
            "max_congestion": 0.94135,
            "path_stretch": 1.9037462312520643,
            "fortz_thorup_sum": 657
        },
        {
            "failed_links#": 4,
            "delivered_packet_rate": 0.8629897684093182,
            "median_congestion": 0.393414,
            "max_congestion": 0.9464,
            "path_stretch": 1.8743241136917208,
            "fortz_thorup_sum": 673
        },
        {
            "failed_links#": 4,
            "delivered_packet_rate": 0.7532712228389364,
            "median_congestion": 0.293095,
            "max_congestion": 0.668543,
            "path_stretch": 1.9172687991040966,
            "fortz_thorup_sum": 127
        },
        {
            "failed_links#": 4,
            "delivered_packet_rate": 0.8156693012422047,
            "median_congestion": 0.235909,
            "max_congestion": 0.755523,
            "path_stretch": 1.8380116383098846,
            "fortz_thorup_sum": 123
        },
        {
            "failed_links#": 4,
            "delivered_packet_rate": 0.9851910003937673,
            "median_congestion": 0.469353,
            "max_congestion": 1.123639,
            "path_stretch": 2.0248165271228067,
            "fortz_thorup_sum": 5739
        },
        {
            "failed_links#": 4,
            "delivered_packet_rate": 0.9625848193175807,
            "median_congestion": 0.411224,
            "max_congestion": 1.077055,
            "path_stretch": 2.0311520278803226,
            "fortz_thorup_sum": 1230
        },
        {
            "failed_links#": 4,
            "delivered_packet_rate": 0.9478051312575693,
            "median_congestion": 0.36836,
            "max_congestion": 1.036671,
            "path_stretch": 1.7016731517934185,
            "fortz_thorup_sum": 1691
        }
    ]
}